<annotation verified="no">
  <folder>image_HH_4</folder>
  <filename>ship_hh_02017012977040701</filename>
  <path>Gao_ship_hh_02017012977040701.xml</path> 
  <source>
    <database>Unknown</database>
  </source>
  <size>
    <width>256</width>
    <height>256</height>
    <depth>3</depth>
  </size>
  <segmented>0</segmented>
  <object>
    <name>ship</name>
    <pose>Unspecified</pose>
    <truncated>0</truncated>
    <Difficult>0</Difficult>
    <bndbox>
      <xmin>129</xmin>
      <ymin>80</ymin>
      <xmax>150</xmax>
      <ymax>101</ymax>
    </bndbox>
  </object>
  <object>
    <name>ship</name>
    <pose>Unspecified</pose>
    <truncated>0</truncated>
    <Difficult>0</Difficult>
    <bndbox>
      <xmin>199</xmin>
      <ymin>200</ymin>
      <xmax>225</xmax>
      <ymax>216</ymax>
    </bndbox>
  </object>
  <object>
    <name>ship</name>
    <pose>Unspecified</pose>
    <truncated>1</truncated>
    <Difficult>0</Difficult>
    <bndbox>
      <xmin>226</xmin>
      <ymin>118</ymin>
      <xmax>256</xmax>
      <ymax>140</ymax>
    </bndbox>
  </object>
</annotation>
