<annotation verified="no">
  <folder>intensity_1</folder>
  <filename>ship_hh_0201710256501010028</filename>
  <path>Gao_ship_hv_0201710256501010028.xml</path> 
  <source>
    <database>Unknown</database>
  </source>
  <size>
    <width>256</width>
    <height>256</height>
    <depth>3</depth>
  </size>
  <segmented>0</segmented>
  <object>
    <name>ship</name>
    <pose>Unspecified</pose>
    <truncated>0</truncated>
    <Difficult>0</Difficult>
    <bndbox>
      <xmin>219</xmin>
      <ymin>105</ymin>
      <xmax>231</xmax>
      <ymax>145</ymax>
    </bndbox>
  </object>
</annotation>
