<annotation verified="no">
  <folder>cal_db_3</folder>
  <filename>ship_hh_0201709013103010013</filename>
  <path>Gao_ship_hh_0201709013103010013.xml</path> 
  <source>
    <database>Unknown</database>
  </source>
  <size>
    <width>256</width>
    <height>256</height>
    <depth>3</depth>
  </size>
  <segmented>0</segmented>
  <object>
    <name>ship</name>
    <pose>Unspecified</pose>
    <truncated>0</truncated>
    <Difficult>0</Difficult>
    <bndbox>
      <xmin>62</xmin>
      <ymin>109</ymin>
      <xmax>103</xmax>
      <ymax>132</ymax>
    </bndbox>
  </object>
  <object>
    <name>ship</name>
    <pose>Unspecified</pose>
    <truncated>0</truncated>
    <Difficult>0</Difficult>
    <bndbox>
      <xmin>113</xmin>
      <ymin>20</ymin>
      <xmax>156</xmax>
      <ymax>44</ymax>
    </bndbox>
  </object>
</annotation>
